string2markup/__init__.py
string2markup-0.0.1.dist-info/METADATA
string2markup-0.0.1.dist-info/WHEEL
string2markup-0.0.1.dist-info/top_level.txt
string2markup-0.0.1.dist-info/RECORD
