Metadata-Version: 2.1
Name: string2markup
Version: 0.0.1
Summary: Made to format strings for kivy/kivymd (MIT)
Home-page: UNKNOWN
Author: hansalemao
Author-email: <aulasparticularesdealemaosp@gmail.com>
License: UNKNOWN
Keywords: markup,markdown,kivy,kivymd
Platform: UNKNOWN
Classifier: Development Status :: 1 - Planning
Classifier: Intended Audience :: Developers
Classifier: Programming Language :: Python :: 3
Classifier: Operating System :: Unix
Classifier: Operating System :: MacOS :: MacOS X
Classifier: Operating System :: Microsoft :: Windows
